{"list":[{"id":"test ID 0","title":"test title 0","description":"test description 0"},{"id":"test ID 1","title":"test title 1","description":"test description 1"},{"id":"test ID 2","title":"test title 2","description":"test description 2"},{"id":"test ID 3","title":"test title 3","description":"test description 3"},{"id":"test ID 4","title":"test title 4","description":"test description 4"},{"id":"a","title":"a","description":"a"},{"id":"","title":"","description":""},{"id":"","title":"","description":""}]}